tcd/__init__.py
tcd/__main__.py
tcd/arguments.py
tcd/downloader.py
tcd/formatter.py
tcd/logger.py
tcd/pipe.py
tcd/safedict.py
tcd/settings.py
tcd/settings.reference.json
tcd/singleton.py
tcd/formats/__init__.py
tcd/formats/custom.py
tcd/formats/format.py
tcd/formats/srt.py
tcd/formats/ssa.py
tcd-3.2.2.dist-info/LICENSE
tcd-3.2.2.dist-info/METADATA
tcd-3.2.2.dist-info/WHEEL
tcd-3.2.2.dist-info/entry_points.txt
tcd-3.2.2.dist-info/top_level.txt
tcd-3.2.2.dist-info/zip-safe
tcd-3.2.2.dist-info/RECORD
