Metadata-Version: 2.1
Name: tcd
Version: 3.2.2
Summary: Twitch Chat Downloader
Home-page: https://github.com/PetterKraabol/Twitch-Chat-Downloader
Author: Petter Kraabøl
Author-email: petter.zarlach@gmail.com
License: MIT
Keywords: Twitch
Platform: UNKNOWN
Classifier: Development Status :: 4 - Beta
Classifier: Intended Audience :: End Users/Desktop
Classifier: License :: OSI Approved :: MIT License
Classifier: Natural Language :: English
Classifier: Programming Language :: Python :: 3.7
Classifier: Programming Language :: Python :: 3.8
Classifier: Programming Language :: Python :: 3.9
Requires-Python: >=3.8
License-File: LICENSE
Requires-Dist: requests (==2.27.1)
Requires-Dist: twitch-python (==0.0.20)
Requires-Dist: pytz (==2022.1)
Requires-Dist: python-dateutil (==2.8.2)
